lcm/lcm.vhdl
LIBRARY IEEE;
USE IEEE.STD_LOGIC_1164.ALL;
USE IEEE.STD_LOGIC_ARITH.ALL;
USE IEEE.STD_LOGIC_UNSIGNED.ALL;

ENTITY fsm_lcm IS
	PORT(
		RESET, CLK : IN STD_LOGIC;
		A, B : IN INTEGER;
		LCM : OUT INTEGER
	);
END ENTITY fsm_lcm;

ARCHITECTURE behavior OF fsm_lcm IS
	TYPE state IS (start, input, calculate, output);
	SIGNAL current_state, next_state : state;
	SIGNAL gcd_value : INTEGER;
BEGIN
	STATE_REGISTER: PROCESS(CLK, RESET)
	BEGIN	
		IF (RESET = '1') THEN
			current_state <= start;
		ELSIF (rising_edge(CLK)) THEN
			current_state <= next_state;
		END IF;
	END PROCESS STATE_REGISTER;

	COMPUTE: PROCESS (A, B, current_state)
	VARIABLE x, y, r : INTEGER;
	BEGIN
		CASE current_state IS
			WHEN start => 
				next_state <= input;
			WHEN input =>
				x := A;
				y := B;
				next_state <= calculate;
			WHEN calculate =>
				while x /= 0 loop
					r := y mod x;
					y := x;
					x := r;
				end loop;
				gcd_value <= y;

				LCM <= A * B / gcd_value;
				next_state <= output;
			WHEN output => 
				next_state <= start;
			WHEN OTHERS => 
				next_state <= start;
		END CASE;
	END PROCESS COMPUTE;
END ARCHITECTURE behavior;

lcm/tb_lcm.vhdl
library ieee;
use ieee.std_logic_1164.all;

entity fsmtb_lcm  is 
	end fsmtb_lcm;

architecture behavior of fsmtb_lcm is 
signal CLK, RESET: std_logic;
signal A, B, LCM: integer;
component fsm_LCM 
	port(CLK, RESET : IN STD_LOGIC;
	    A, B: IN INTEGER;
	    LCM : OUT INTEGER);
END COMPONENT;
BEGIN
fsm_LCM1 : fsm_LCM port map(CLK=> CLK, RESET=>  RESET, A=>A, B=>B, LCM=>LCM);
clock: process
begin
	CLK<= '1';
	wait for 100 ns;

	CLK <= '0';
	WAIT FOR 100 NS;
	
end process;
process
begin
	RESET <= '1';
	wait for 10 ns;
	RESET <= '0';

	A <= 45;
	B <= 15;
	wait for 1600 ns;

	A <= 8;
	B <= 10;
	wait for 1600 ns;

	A <= 15;
	B <= 55;
	wait for 1600 ns;

	WAIT;
end process;
end behavior;

lcm/result.vcd
$date
  Fri Feb  2 17:41:40 2024
$end
$version
  GHDL v0
$end
$timescale
  1 fs
$end
$scope module standard $end
$upscope $end
$scope module std_logic_1164 $end
$upscope $end
$scope module std_logic_arith $end
$upscope $end
$scope module std_logic_unsigned $end
$upscope $end
$scope module fsmtb_lcm $end
$var reg 1 ! clk $end
$var reg 1 " reset $end
$var integer 32 # a $end
$var integer 32 $ b $end
$var integer 32 % lcm $end
$scope module fsm_lcm1 $end
$var reg 1 & reset $end
$var reg 1 ' clk $end
$var integer 32 ( a $end
$var integer 32 ) b $end
$var integer 32 * lcm $end
$comment current_state is not handled $end
$comment next_state is not handled $end
$var integer 32 + gcd_value $end
$upscope $end
$upscope $end
$enddefinitions $end
#0
1!
1"
b10000000000000000000000000000000 #
b10000000000000000000000000000000 $
b10000000000000000000000000000000 %
1&
1'
b10000000000000000000000000000000 (
b10000000000000000000000000000000 )
b10000000000000000000000000000000 *
b10000000000000000000000000000000 +
#10000000
0"
b101101 #
b1111 $
0&
b101101 (
b1111 )
#100000000
0!
0'
#200000000
1!
1'
#300000000
0!
0'
#400000000
1!
b0 %
1'
b0 *
b1111 +
#500000000
0!
0'
#600000000
1!
1'
#700000000
0!
0'
#800000000
1!
1'
#900000000
0!
0'
#1000000000
1!
1'
#1100000000
0!
0'
#1200000000
1!
b101101 %
1'
b101101 *
#1300000000
0!
0'
#1400000000
1!
1'
#1500000000
0!
0'
#1600000000
1!
1'
#1610000000
b1000 #
b1010 $
b1000 (
b1010 )
#1700000000
0!
0'
#1800000000
1!
1'
#1900000000
0!
0'
#2000000000
1!
b101 %
1'
b101 *
b10 +
#2100000000
0!
0'
#2200000000
1!
1'
#2300000000
0!
0'
#2400000000
1!
1'
#2500000000
0!
0'
#2600000000
1!
1'
#2700000000
0!
0'
#2800000000
1!
b101000 %
1'
b101000 *
#2900000000
0!
0'
#3000000000
1!
1'
#3100000000
0!
0'
#3200000000
1!
1'
#3210000000
b1111 #
b110111 $
b1111 (
b110111 )
#3300000000
0!
0'
#3400000000
1!
1'
#3500000000
0!
0'
#3600000000
1!
b110011100 %
1'
b110011100 *
b101 +
#3700000000
0!
0'
#3800000000
1!
1'
#3900000000
0!
0'
#4000000000
1!
1'
#4100000000
0!
0'
#4200000000
1!
1'
#4300000000
0!
0'
#4400000000
1!
b10100101 %
1'
b10100101 *
