1-8-Demultiplexer/oneEight.vhdl
library	IEEE;
use	IEEE.STD_LOGIC_1164.ALL;
use	IEEE.STD_LOGIC_ARITH.ALL;
use	IEEE.STD_LOGIC_UNSIGNED.ALL;

entity oneEight	is

port(
	input:	in	STD_LOGIC;
	selection	:	in	STD_LOGIC_VECTOR(2	downto	0);
	output_0	:	out	STD_LOGIC;
	output_1	:	out	STD_LOGIC;
	output_2	:	out	STD_LOGIC;
	output_3	:	out	STD_LOGIC;
	output_4	:	out	STD_LOGIC;
	output_5	:	out	STD_LOGIC;
	output_6	:	out	STD_LOGIC;
	output_7	:	out	STD_LOGIC
	);
end oneEight;

architecture	behavior	of	oneEight	is
begin
	ha:	process(input,	selection)
	begin
		case	selection	is
			when	"000"	=>
				output_0	<=	input;
				output_1	<=	'0';
				output_2	<=	'0';
				output_3	<=	'0';
				output_4	<=	'0';
				output_5	<=	'0';
				output_6	<=	'0';
				output_7	<=	'0';
	
			when	"001"	=>
				output_0	<=	'0';
				output_1	<=	input;
				output_2	<=	'0';
				output_3	<=	'0';
				output_4	<=	'0';
				output_5	<=	'0';
				output_6	<=	'0';
				output_7	<=	'0';
	
			when	"010"	=>
				output_0	<=	'0';
				output_1	<=	'0';
				output_2	<=	input;
				output_3	<=	'0';
				output_4	<=	'0';
				output_5	<=	'0';
				output_6	<=	'0';
				output_7	<=	'0';
	
			when	"011"	=>
				output_0	<=	'0';
				output_1	<=	'0';
				output_2	<=	'0';
				output_3	<=	input;
				output_4	<=	'0';
				output_5	<=	'0';
				output_6	<=	'0';
				output_7	<=	'0';
	
			when	"100"	=>
				output_0	<=	'0';
				output_1	<=	'0';
				output_2	<=	'0';
				output_3	<=	'0';
				output_4	<=	input;
				output_5	<=	'0';
				output_6	<=	'0';
				output_7	<=	'0';
	
			when	"101"	=>
				output_0	<=	'0';
				output_1	<=	'0';
				output_2	<=	'0';
				output_3	<=	'0';
				output_4	<=	'0';
				output_5	<=	input;
				output_6	<=	'0';
				output_7	<=	'0';
	

	
			when	"110"	=>
				output_0	<=	'0';
				output_1	<=	'0';
				output_2	<=	'0';
				output_3	<=	'0';
				output_4	<=	'0';
				output_5	<=	'0';
				output_6	<=	input;
				output_7	<=	'0';
	

	
			when	"111"	=>
				output_0	<=	'0';
				output_1	<=	'0';
				output_2	<=	'0';
				output_3	<=	'0';
				output_4	<=	'0';
				output_5	<=	'0';
				output_6	<=	'0';
				output_7	<=	input;
			when	others	=>
				null;
		end	case;
	end	process;
end	behavior;

1-8-Demultiplexer/test_oneEight.vhdl
library IEEE;
use IEEE.STD_LOGIC_1164.ALL;
use IEEE.STD_LOGIC_ARITH.ALL;
use IEEE.STD_LOGIC_UNSIGNED.ALL;

entity test_oneEight is
end test_oneEight;

architecture test of test_oneEight is
    signal tb_input : STD_LOGIC := '0';
    signal tb_selection : STD_LOGIC_VECTOR(2 downto 0) := "000";
    signal tb_output_0, tb_output_1, tb_output_2, tb_output_3, tb_output_4, tb_output_5, tb_output_6, tb_output_7 : STD_LOGIC;

    component oneEight
        port (
            input     : in  STD_LOGIC;
            selection : in  STD_LOGIC_VECTOR(2 downto 0);
            output_0  : out STD_LOGIC;
            output_1  : out STD_LOGIC;
            output_2  : out STD_LOGIC;
            output_3  : out STD_LOGIC;
            output_4  : out STD_LOGIC;
            output_5  : out STD_LOGIC;
            output_6  : out STD_LOGIC;
            output_7  : out STD_LOGIC
        );
    end component;

begin
    uut : oneEight
        port map (
            input     => tb_input,
            selection => tb_selection,
            output_0  => tb_output_0,
            output_1  => tb_output_1,
            output_2  => tb_output_2,
            output_3  => tb_output_3,
            output_4  => tb_output_4,
            output_5  => tb_output_5,
            output_6  => tb_output_6,
            output_7  => tb_output_7
        );

    process
    begin
        -- Test case 1
        tb_input <= '1';
        tb_selection <= "000";
        wait for 10 ns;

        -- Test case 2
        tb_input <= '1';
        tb_selection <= "001";
        wait for 10 ns;

	tb_input	<=	'1';
	tb_selection	<=	"010";
	wait for 10 ns;
	
	tb_input	<=	'0';
	tb_selection	<=	"011";
	wait for 10 ns;

	tb_input	<=	'1';
	tb_selection	<=	"100";
	wait for 10 ns;

	tb_input	<=	'1';
	tb_selection	<=	"101";
	wait for 10 ns;

	tb_input	<=	'1';
	tb_selection	<=	"110";
	wait for 10 ns;
	
	tb_input	<=	'1';
	tb_selection	<=	"111";
	wait for 10 ns;
	
     -- Add more test cases as needed

        wait;
    end process;

end test;

1-8-Demultiplexer/result.vcd
$date
  Mon Jan 29 21:23:20 2024
$end
$version
  GHDL v0
$end
$timescale
  1 fs
$end
$scope module standard $end
$upscope $end
$scope module std_logic_1164 $end
$upscope $end
$scope module std_logic_arith $end
$upscope $end
$scope module std_logic_unsigned $end
$upscope $end
$scope module test_oneeight $end
$var reg 1 ! tb_input $end
$var reg 3 " tb_selection[2:0] $end
$var reg 1 # tb_output_0 $end
$var reg 1 $ tb_output_1 $end
$var reg 1 % tb_output_2 $end
$var reg 1 & tb_output_3 $end
$var reg 1 ' tb_output_4 $end
$var reg 1 ( tb_output_5 $end
$var reg 1 ) tb_output_6 $end
$var reg 1 * tb_output_7 $end
$scope module uut $end
$var reg 1 + input $end
$var reg 3 , selection[2:0] $end
$var reg 1 - output_0 $end
$var reg 1 . output_1 $end
$var reg 1 / output_2 $end
$var reg 1 0 output_3 $end
$var reg 1 1 output_4 $end
$var reg 1 2 output_5 $end
$var reg 1 3 output_6 $end
$var reg 1 4 output_7 $end
$upscope $end
$upscope $end
$enddefinitions $end
#0
1!
b000 "
1#
0$
0%
0&
0'
0(
0)
0*
1+
b000 ,
1-
0.
0/
00
01
02
03
04
#10000000
b001 "
0#
1$
b001 ,
0-
1.
#20000000
b010 "
0$
1%
b010 ,
0.
1/
#30000000
0!
b011 "
0%
0+
b011 ,
0/
#40000000
1!
b100 "
1'
1+
b100 ,
11
#50000000
b101 "
0'
1(
b101 ,
01
12
#60000000
b110 "
0(
1)
b110 ,
02
13
#70000000
b111 "
0)
1*
b111 ,
03
14
