sequence_1101/seq_1101.vhdl
LIBRARY IEEE;
USE	IEEE.STD_LOGIC_1164.ALL;

ENTITY	seq_1101	is
PORT(
	X: in STD_LOGIC;
	CLK, RST : in STD_LOGIC;
	Z :	out STD_LOGIC
);
END	seq_1101;

ARCHITECTURE behavior of seq_1101 is
type state is (Q0, Q1, Q2, Q3, Q4);
signal currentState, nextState: state;

begin

seq_proc: process(CLK, RST) is
begin

if(RST='1') then
	currentState<=Q0;
elsif(rising_edge(CLK)) then
	currentState<=nextState;
end if;
end process seq_proc;

comb_proc: process(currentState, X) is
begin

case(currentState) is
	when Q0 =>
	if(X='1') then 
		nextState <= Q1;
	else
		nextState <= Q0;
	end if;

	when Q1 =>
	if(X='1') then
		nextState <= Q2;
	else
		nextState <= Q0;
	end if;

	when Q2 => 
	if(X='0') then
		nextState <= Q3;
	else
		nextState <= Q2;
	end if;
	
	when Q3 =>
	if(X='1') then
		nextState <=Q4;
	else
		nextState <=Q0;
	end if;
	when Q4 =>
	if(X='0') then
		nextState <= Q0;
	else
		nextState <= Q1;
	end if;

end case;
end process comb_proc;


out_proc: process(currentState) is
begin
	case currentState is
	when Q0 =>
	Z <= '0';
	when Q1 =>
        Z <= '0';
	when Q2 =>
	Z <= '0';
	when Q3 =>
	Z <= '0';
	when Q4 =>
	Z <= '1';
	end case;
end process out_proc;
end behavior;

sequence_1101/test_1101.vhdl
LIBRARY ieee;
USE ieee.std_logic_1164.ALL;
 
ENTITY testbench IS
END testbench;
 
ARCHITECTURE testArch OF testbench IS 
   
    COMPONENT seq_1101
    PORT(
         CLK : IN  std_logic;
         RST : IN  std_logic;
         X : IN  std_logic;
         Z : OUT  std_logic
        );
    END COMPONENT;
    

    signal CLK,RST,X : std_logic := '0';
    signal Z : std_logic;

 constant CLK_period : time := 10 ns;
 
BEGIN
   uut: seq_1101 PORT MAP (
          CLK => CLK,
          RST => RST,
          X => X,
          Z => Z
        );

    CLK_process :process
    begin
    
    CLK <= '0';
    wait for CLK_period/2;
    CLK <= '1';
    wait for CLK_period/2;
    
    end process;
 

    stimulus_proc: process
    begin  
    
    X <= '0';
    RST <= '1';
    wait for 30 ns;

    RST <= '0';
    wait for 40 ns;
    
    X <= '1';
    wait for 10 ns;
    X <= '0';
    wait for 10 ns;
    X <= '1'; 
    wait for 10 ns;
    X <= '1'; 
    wait for 10 ns;
    X <= '0'; 
    wait for 10 ns;
    X <= '1';
    wait for 10 ns;
    X <= '0'; 
    wait for 10 ns;
    X <= '1';
    wait for 10 ns;
    X <= '0';
    wait for 10 ns;
    X <= '1';
    wait for 10 ns;
    X <= '1';
    wait for 10 ns;
    X <= '0';
    wait for 10 ns;
    X <= '1';
    wait for 10 ns;

    
    wait;
   end process stimulus_proc;

end testArch;

sequence_1101/result.vcd
$date
  Wed Feb  7 14:27:54 2024
$end
$version
  GHDL v0
$end
$timescale
  1 fs
$end
$scope module standard $end
$upscope $end
$scope module std_logic_1164 $end
$upscope $end
$scope module testbench $end
$var reg 1 ! clk $end
$var reg 1 " rst $end
$var reg 1 # x $end
$var reg 1 $ z $end
$scope module uut $end
$var reg 1 % x $end
$var reg 1 & clk $end
$var reg 1 ' rst $end
$var reg 1 ( z $end
$comment currentstate is not handled $end
$comment nextstate is not handled $end
$upscope $end
$upscope $end
$enddefinitions $end
#0
0!
1"
0#
0$
0%
0&
1'
0(
#5000000
1!
1&
#10000000
0!
0&
#15000000
1!
1&
#20000000
0!
0&
#25000000
1!
1&
#30000000
0!
0"
0&
0'
#35000000
1!
1&
#40000000
0!
0&
#45000000
1!
1&
#50000000
0!
0&
#55000000
1!
1&
#60000000
0!
0&
#65000000
1!
1&
#70000000
0!
1#
1%
0&
#75000000
1!
1&
#80000000
0!
0#
0%
0&
#85000000
1!
1&
#90000000
0!
1#
1%
0&
#95000000
1!
1&
#100000000
0!
0&
#105000000
1!
1&
#110000000
0!
0#
0%
0&
#115000000
1!
1&
#120000000
0!
1#
1%
0&
#125000000
1!
1$
1&
1(
#130000000
0!
0#
0%
0&
#135000000
1!
0$
1&
0(
#140000000
0!
1#
1%
0&
#145000000
1!
1&
#150000000
0!
0#
0%
0&
#155000000
1!
1&
#160000000
0!
1#
1%
0&
#165000000
1!
1&
#170000000
0!
0&
#175000000
1!
1&
#180000000
0!
0#
0%
0&
#185000000
1!
1&
#190000000
0!
1#
1%
0&
#195000000
1!
1$
1&
1(
#200000000
0!
0&
#205000000
1!
0$
1&
0(
